jparse_robotics/__init__.py
jparse_robotics/core.py
jparse_robotics/robot.py
jparse_robotics/ros/__init__.py
jparse_robotics/ros/ros_robot.py
jparse_robotics-0.1.0.dist-info/METADATA
jparse_robotics-0.1.0.dist-info/WHEEL
jparse_robotics-0.1.0.dist-info/licenses/LICENSE
jparse_robotics-0.1.0.dist-info/RECORD
