Metadata-Version: 2.4
Name: jparse-robotics
Version: 0.1.0
Summary: J-PARSE: Jacobian-based Projection Algorithm for Resolving Singularities Effectively in inverse kinematic control of serial manipulators
Project-URL: Homepage, https://github.com/armlabstanford/jparse
Project-URL: Documentation, https://github.com/armlabstanford/jparse#readme
Project-URL: Repository, https://github.com/armlabstanford/jparse
Project-URL: Paper, https://arxiv.org/abs/2505.00306
Author: Shivani Guptasarma, Matthew Strong, Honghao Zhen
Author-email: Monroe Kennedy III <monroek@stanford.edu>
License: MIT
License-File: LICENSE
Keywords: control,inverse-kinematics,jacobian,kinematics,manipulator,robotics,singularity
Classifier: Development Status :: 4 - Beta
Classifier: Intended Audience :: Science/Research
Classifier: License :: OSI Approved :: MIT License
Classifier: Operating System :: OS Independent
Classifier: Programming Language :: Python :: 3
Classifier: Programming Language :: Python :: 3.9
Classifier: Programming Language :: Python :: 3.10
Classifier: Programming Language :: Python :: 3.11
Classifier: Programming Language :: Python :: 3.12
Classifier: Topic :: Scientific/Engineering
Classifier: Topic :: Scientific/Engineering :: Physics
Requires-Python: >=3.9
Requires-Dist: numpy>=1.20.0
Provides-Extra: all
Requires-Dist: black; extra == 'all'
Requires-Dist: mypy; extra == 'all'
Requires-Dist: pin; extra == 'all'
Requires-Dist: pytest-cov; extra == 'all'
Requires-Dist: pytest>=7.0; extra == 'all'
Requires-Dist: ruff; extra == 'all'
Provides-Extra: dev
Requires-Dist: black; extra == 'dev'
Requires-Dist: mypy; extra == 'dev'
Requires-Dist: pytest-cov; extra == 'dev'
Requires-Dist: pytest>=7.0; extra == 'dev'
Requires-Dist: ruff; extra == 'dev'
Provides-Extra: pinocchio
Requires-Dist: pin; extra == 'pinocchio'
